din.py
din-0.5.0.dist-info/METADATA
din-0.5.0.dist-info/RECORD
din-0.5.0.dist-info/WHEEL
din-0.5.0.dist-info/top_level.txt
